BSplineFit/__init__.py
BSplineFit/cubic_spline.py
BSplineFit/optimization.py
BSplineFit/tree.py
BSplineFit-1.1.0.dist-info/LICENSE
BSplineFit-1.1.0.dist-info/METADATA
BSplineFit-1.1.0.dist-info/WHEEL
BSplineFit-1.1.0.dist-info/top_level.txt
BSplineFit-1.1.0.dist-info/RECORD
